pycac/CacClass.py
pycac/ConverterWidgetClass.py
pycac/DownloadWidgetClass.py
pycac/InputClass.py
pycac/InputWidgetClass.py
pycac/MainWindow.py
pycac/RestartWidgetClass.py
pycac/SelectionWidgetClass.py
pycac/SetupWindow.py
pycac/SubmissionWidgetClass.py
pycac/SubmitWidgetClass.py
pycac/__init__.py
pycac/__main__.py
pycac/downloads.py
pycac/icon.png
pycac/install.py
pycac/installWidget.py
pycac/interface.py
pycac/ssh_util.py
pycac/template.pbs
pycac/template.sl
pycac/uploads.py
pycac/vtk2dump.py
pycac-0.2.5.dist-info/METADATA
pycac-0.2.5.dist-info/RECORD
pycac-0.2.5.dist-info/WHEEL
pycac-0.2.5.dist-info/top_level.txt
