Metadata-Version: 2.1
Name: pycac
Version: 0.2.5
Summary: Graphical user interface for CAC simulator
Home-page: http://www.pycac.org
Author: Kevin Chu, Alex Selimov, Shuozhi Xu
Author-email: kchu41@gatech.edu
License: UNKNOWN
Keywords: concurrent atomistic continuum simulation interface
Platform: UNKNOWN
Classifier: Development Status :: 3 - Alpha
Classifier: License :: OSI Approved :: Apache Software License
Classifier: Programming Language :: Python :: 3.6
Requires-Python: >=3.6
Requires-Dist: paramiko
Requires-Dist: pyqt5
Requires-Dist: numpy
